loghtml/__init__.py
loghtml/config.py
loghtml/core.py
loghtml/template.html
loghtml/template.py
loghtml/writer.py
loghtml-0.1.23.dist-info/licenses/LICENSE
loghtml-0.1.23.dist-info/METADATA
loghtml-0.1.23.dist-info/WHEEL
loghtml-0.1.23.dist-info/top_level.txt
loghtml-0.1.23.dist-info/RECORD
